plant_ia/__init__.py
plant_ia-1.2.2.dist-info/LICENSE
plant_ia-1.2.2.dist-info/METADATA
plant_ia-1.2.2.dist-info/WHEEL
plant_ia-1.2.2.dist-info/top_level.txt
plant_ia-1.2.2.dist-info/RECORD
