Metadata-Version: 2.1
Name: plant-ia
Version: 1.2.2
Summary: Librería en español para estructurar prompts dinámicos con IA
Home-page: https://github.com/DISTinTheHouse/plant-ia
Author: Jesús Alberto Ibarra Morales
Author-email: ufkwear@gmail.com
Classifier: Programming Language :: Python :: 3
Classifier: License :: OSI Approved :: MIT License
Classifier: Natural Language :: Spanish
Classifier: Topic :: Scientific/Engineering :: Artificial Intelligence
Requires-Python: >=3.6
License-File: LICENSE
